medium_multi/__init__.py
medium_multi/multi.py
medium_multi/stats.py
tests/__init__.py
tests/multi_tests.py
mediumvers123-0.1.2.dist-info/METADATA
mediumvers123-0.1.2.dist-info/WHEEL
mediumvers123-0.1.2.dist-info/top_level.txt
mediumvers123-0.1.2.dist-info/RECORD
